obsidian_wrapper/__init__.py
obsidian_wrapper/markdown_object.py
obsidian_wrapper/obsidian_markdown_file.py
obsidian_wrapper/obsidian_vault.py
obsidian_wrapper/utils.py
obsidian_wrapper-0.1.0.dist-info/LICENSE
obsidian_wrapper-0.1.0.dist-info/METADATA
obsidian_wrapper-0.1.0.dist-info/WHEEL
obsidian_wrapper-0.1.0.dist-info/top_level.txt
obsidian_wrapper-0.1.0.dist-info/RECORD
