Metadata-Version: 2.1
Name: obsidian-wrapper
Version: 0.1.0
Summary: A wrapper for Obsidian vaults.
Author-email: Ghazanfar Shahbaz <ghazanfarshahbaz2409@gmail.com>
Project-URL: Homepage, https://github.com/GhazanfarShahbaz/ObsidianWrapper
Classifier: Programming Language :: Python :: 3
Classifier: License :: OSI Approved :: MIT License
Classifier: Operating System :: OS Independent
Requires-Python: >=3.11
License-File: LICENSE
Requires-Dist: typing ==3.7.4.3
